fin_summary/__init__.py
fin_summary/main.py
fin_summary/prompts.py
fin_summary-2025.12.21235235.dist-info/METADATA
fin_summary-2025.12.21235235.dist-info/WHEEL
fin_summary-2025.12.21235235.dist-info/top_level.txt
fin_summary-2025.12.21235235.dist-info/RECORD
