Metadata-Version: 2.4
Name: fin-summary
Version: 2025.12.21235235
Summary: fin-summary analyzes financial transaction problems, extracting issue details and creating structured summaries with recommended actions.
Author-email: fin-summary <hi@eugene.plus>
License: MIT
Project-URL: Homepage, https://github.com/chigwell/fin-summary
Requires-Python: >=3.9
Requires-Dist: langchain-llm7>=0.0.0
Requires-Dist: llmatch-messages>=0.0.0
Requires-Dist: langchain-core>=0.3.0
